{
"thermal:beekeeper_boots":[
      {
        "attribute":"footwork:max_fracture",
        "modify":"0.25",
        "operation":"ADDITION"
      },
      {
        "attribute":"footwork:posture_regen",
        "modify":"6.67",
        "operation":"ADDITION"
      },
      {
        "attribute":"footwork:stealth",
        "modify":"-0.4",
        "operation":"ADDITION"
      }
    ],
"thermal:beekeeper_chestplate":[
      {
        "attribute":"footwork:max_fracture",
        "modify":"0.25",
        "operation":"ADDITION"
      },
      {
        "attribute":"footwork:posture_regen",
        "modify":"13.33",
        "operation":"ADDITION"
      },
      {
        "attribute":"footwork:stealth",
        "modify":"-0.8",
        "operation":"ADDITION"
      }
    ],
"thermal:beekeeper_helmet":[
      {
        "attribute":"footwork:max_fracture",
        "modify":"0.25",
        "operation":"ADDITION"
      },
      {
        "attribute":"footwork:posture_regen",
        "modify":"6.67",
        "operation":"ADDITION"
      },
      {
        "attribute":"footwork:stealth",
        "modify":"-0.4",
        "operation":"ADDITION"
      }
    ],
"thermal:beekeeper_leggings":[
      {
        "attribute":"footwork:max_fracture",
        "modify":"0.25",
        "operation":"ADDITION"
      },
      {
        "attribute":"footwork:posture_regen",
        "modify":"10",
        "operation":"ADDITION"
      },
      {
        "attribute":"footwork:stealth",
        "modify":"-0.6",
        "operation":"ADDITION"
      }
    ],
"thermal:diving_boots":[
      {
        "attribute":"footwork:max_fracture",
        "modify":"0.25",
        "operation":"ADDITION"
      },
      {
        "attribute":"footwork:posture_regen",
        "modify":"6.67",
        "operation":"ADDITION"
      },
      {
        "attribute":"footwork:stealth",
        "modify":"-0.4",
        "operation":"ADDITION"
      }
    ],
"thermal:diving_chestplate":[
      {
        "attribute":"footwork:max_fracture",
        "modify":"0.25",
        "operation":"ADDITION"
      },
      {
        "attribute":"footwork:posture_regen",
        "modify":"13.33",
        "operation":"ADDITION"
      },
      {
        "attribute":"footwork:stealth",
        "modify":"-0.8",
        "operation":"ADDITION"
      }
    ],
"thermal:diving_helmet":[
      {
        "attribute":"footwork:max_fracture",
        "modify":"0.25",
        "operation":"ADDITION"
      },
      {
        "attribute":"footwork:posture_regen",
        "modify":"6.67",
        "operation":"ADDITION"
      },
      {
        "attribute":"footwork:stealth",
        "modify":"-0.4",
        "operation":"ADDITION"
      }
    ],
"thermal:diving_leggings":[
      {
        "attribute":"footwork:max_fracture",
        "modify":"0.25",
        "operation":"ADDITION"
      },
      {
        "attribute":"footwork:posture_regen",
        "modify":"10",
        "operation":"ADDITION"
      },
      {
        "attribute":"footwork:stealth",
        "modify":"-0.6",
        "operation":"ADDITION"
      }
    ],
"thermal:hazmat_boots":[
      {
        "attribute":"footwork:max_fracture",
        "modify":"0.25",
        "operation":"ADDITION"
      },
      {
        "attribute":"footwork:posture_regen",
        "modify":"6.67",
        "operation":"ADDITION"
      },
      {
        "attribute":"footwork:stealth",
        "modify":"-0.4",
        "operation":"ADDITION"
      }
    ],
"thermal:hazmat_chestplate":[
      {
        "attribute":"footwork:max_fracture",
        "modify":"0.25",
        "operation":"ADDITION"
      },
      {
        "attribute":"footwork:posture_regen",
        "modify":"13.33",
        "operation":"ADDITION"
      },
      {
        "attribute":"footwork:stealth",
        "modify":"-0.8",
        "operation":"ADDITION"
      }
    ],
"thermal:hazmat_helmet":[
      {
        "attribute":"footwork:max_fracture",
        "modify":"0.25",
        "operation":"ADDITION"
      },
      {
        "attribute":"footwork:posture_regen",
        "modify":"6.67",
        "operation":"ADDITION"
      },
      {
        "attribute":"footwork:stealth",
        "modify":"-0.4",
        "operation":"ADDITION"
      }
    ],
"thermal:hazmat_leggings":[
      {
        "attribute":"footwork:max_fracture",
        "modify":"0.25",
        "operation":"ADDITION"
      },
      {
        "attribute":"footwork:posture_regen",
        "modify":"10",
        "operation":"ADDITION"
      },
      {
        "attribute":"footwork:stealth",
        "modify":"-0.6",
        "operation":"ADDITION"
      }
    ]
}
