{
"wyrmroost:blue_geode_boots":[
      {
        "attribute":"footwork:evasion",
        "modify":"0.3",
        "operation":"ADDITION"
      },
      {
        "attribute":"footwork:max_posture",
        "modify":"1.04",
        "operation":"ADDITION"
      },
      {
        "attribute":"footwork:max_fracture",
        "modify":"0.89",
        "operation":"ADDITION"
      }
    ],
"wyrmroost:blue_geode_chestplate":[
      {
        "attribute":"footwork:evasion",
        "modify":"0.6",
        "operation":"ADDITION"
      },
      {
        "attribute":"footwork:max_posture",
        "modify":"2.08",
        "operation":"ADDITION"
      },
      {
        "attribute":"footwork:max_fracture",
        "modify":"1.53",
        "operation":"ADDITION"
      }
    ],
"wyrmroost:blue_geode_helmet":[
      {
        "attribute":"footwork:evasion",
        "modify":"0.3",
        "operation":"ADDITION"
      },
      {
        "attribute":"footwork:max_posture",
        "modify":"1.04",
        "operation":"ADDITION"
      },
      {
        "attribute":"footwork:max_fracture",
        "modify":"0.89",
        "operation":"ADDITION"
      }
    ],
"wyrmroost:blue_geode_leggings":[
      {
        "attribute":"footwork:evasion",
        "modify":"0.45",
        "operation":"ADDITION"
      },
      {
        "attribute":"footwork:max_posture",
        "modify":"1.56",
        "operation":"ADDITION"
      },
      {
        "attribute":"footwork:max_fracture",
        "modify":"1.21",
        "operation":"ADDITION"
      }
    ],
"wyrmroost:drake_boots":[
      {
        "attribute":"footwork:posture_regen",
        "modify":"0.53",
        "operation":"ADDITION"
      },
      {
        "attribute":"footwork:max_fracture",
        "modify":"0.81",
        "operation":"ADDITION"
      }
    ],
"wyrmroost:drake_chestplate":[
      {
        "attribute":"footwork:posture_regen",
        "modify":"1.06",
        "operation":"ADDITION"
      },
      {
        "attribute":"footwork:max_fracture",
        "modify":"1.37",
        "operation":"ADDITION"
      }
    ],
"wyrmroost:drake_helmet":[
      {
        "attribute":"footwork:posture_regen",
        "modify":"0.53",
        "operation":"ADDITION"
      },
      {
        "attribute":"footwork:max_fracture",
        "modify":"0.81",
        "operation":"ADDITION"
      }
    ],
"wyrmroost:drake_leggings":[
      {
        "attribute":"footwork:posture_regen",
        "modify":"0.79",
        "operation":"ADDITION"
      },
      {
        "attribute":"footwork:max_fracture",
        "modify":"1.09",
        "operation":"ADDITION"
      }
    ],
"wyrmroost:platinum_boots":[
      {
        "attribute":"footwork:evasion",
        "modify":"1.2",
        "operation":"ADDITION"
      },
      {
        "attribute":"footwork:max_posture",
        "modify":"2.08",
        "operation":"ADDITION"
      },
      {
        "attribute":"footwork:max_fracture",
        "modify":"0.25",
        "operation":"ADDITION"
      }
    ],
"wyrmroost:platinum_chestplate":[
      {
        "attribute":"footwork:evasion",
        "modify":"2.4",
        "operation":"ADDITION"
      },
      {
        "attribute":"footwork:max_posture",
        "modify":"4.16",
        "operation":"ADDITION"
      },
      {
        "attribute":"footwork:max_fracture",
        "modify":"0.25",
        "operation":"ADDITION"
      }
    ],
"wyrmroost:platinum_helmet":[
      {
        "attribute":"footwork:evasion",
        "modify":"1.2",
        "operation":"ADDITION"
      },
      {
        "attribute":"footwork:max_posture",
        "modify":"2.08",
        "operation":"ADDITION"
      },
      {
        "attribute":"footwork:max_fracture",
        "modify":"0.25",
        "operation":"ADDITION"
      }
    ],
"wyrmroost:platinum_leggings":[
      {
        "attribute":"footwork:evasion",
        "modify":"1.8",
        "operation":"ADDITION"
      },
      {
        "attribute":"footwork:max_posture",
        "modify":"3.12",
        "operation":"ADDITION"
      },
      {
        "attribute":"footwork:max_fracture",
        "modify":"0.25",
        "operation":"ADDITION"
      }
    ],
"wyrmroost:purple_geode_boots":[
      {
        "attribute":"footwork:evasion",
        "modify":"0.4",
        "operation":"ADDITION"
      },
      {
        "attribute":"footwork:max_posture",
        "modify":"1.2",
        "operation":"ADDITION"
      },
      {
        "attribute":"footwork:max_fracture",
        "modify":"0.97",
        "operation":"ADDITION"
      }
    ],
"wyrmroost:purple_geode_chestplate":[
      {
        "attribute":"footwork:evasion",
        "modify":"0.8",
        "operation":"ADDITION"
      },
      {
        "attribute":"footwork:max_posture",
        "modify":"2.4",
        "operation":"ADDITION"
      },
      {
        "attribute":"footwork:max_fracture",
        "modify":"1.69",
        "operation":"ADDITION"
      }
    ],
"wyrmroost:purple_geode_helmet":[
      {
        "attribute":"footwork:evasion",
        "modify":"0.4",
        "operation":"ADDITION"
      },
      {
        "attribute":"footwork:max_posture",
        "modify":"1.2",
        "operation":"ADDITION"
      },
      {
        "attribute":"footwork:max_fracture",
        "modify":"0.97",
        "operation":"ADDITION"
      }
    ],
"wyrmroost:purple_geode_leggings":[
      {
        "attribute":"footwork:evasion",
        "modify":"0.6",
        "operation":"ADDITION"
      },
      {
        "attribute":"footwork:max_posture",
        "modify":"1.8",
        "operation":"ADDITION"
      },
      {
        "attribute":"footwork:max_fracture",
        "modify":"1.33",
        "operation":"ADDITION"
      }
    ],
"wyrmroost:red_geode_boots":[
      {
        "attribute":"footwork:evasion",
        "modify":"0.4",
        "operation":"ADDITION"
      },
      {
        "attribute":"footwork:max_posture",
        "modify":"1.2",
        "operation":"ADDITION"
      },
      {
        "attribute":"footwork:max_fracture",
        "modify":"0.89",
        "operation":"ADDITION"
      }
    ],
"wyrmroost:red_geode_chestplate":[
      {
        "attribute":"footwork:evasion",
        "modify":"0.8",
        "operation":"ADDITION"
      },
      {
        "attribute":"footwork:max_posture",
        "modify":"2.4",
        "operation":"ADDITION"
      },
      {
        "attribute":"footwork:max_fracture",
        "modify":"1.53",
        "operation":"ADDITION"
      }
    ],
"wyrmroost:red_geode_helmet":[
      {
        "attribute":"footwork:evasion",
        "modify":"0.4",
        "operation":"ADDITION"
      },
      {
        "attribute":"footwork:max_posture",
        "modify":"1.2",
        "operation":"ADDITION"
      },
      {
        "attribute":"footwork:max_fracture",
        "modify":"0.89",
        "operation":"ADDITION"
      }
    ],
"wyrmroost:red_geode_leggings":[
      {
        "attribute":"footwork:evasion",
        "modify":"0.6",
        "operation":"ADDITION"
      },
      {
        "attribute":"footwork:max_posture",
        "modify":"1.8",
        "operation":"ADDITION"
      },
      {
        "attribute":"footwork:max_fracture",
        "modify":"1.21",
        "operation":"ADDITION"
      }
    ]
}
